habanero/__init__.py
habanero/cn_formats.py
habanero/cnrequest.py
habanero/exceptions.py
habanero/filterhandler.py
habanero/habanero_utils.py
habanero/noworks.py
habanero/request.py
habanero/request_class.py
habanero/response.py
habanero/cn/__init__.py
habanero/cn/cn.py
habanero/cn/constants.py
habanero/cn/styles.py
habanero/counts/__init__.py
habanero/counts/counts.py
habanero/crossref/__init__.py
habanero/crossref/crossref.py
habanero/crossref/filters.py
habanero/crossref/workscontainer.py
habanero-1.2.6.dist-info/LICENSE.rst
habanero-1.2.6.dist-info/METADATA
habanero-1.2.6.dist-info/WHEEL
habanero-1.2.6.dist-info/top_level.txt
habanero-1.2.6.dist-info/RECORD
