Metadata-Version: 2.1
Name: habanero
Version: 1.2.6
Summary: Low Level Client for Crossref Search API
Home-page: https://github.com/sckott/habanero
Author: Scott Chamberlain
Author-email: myrmecocystus@gmail.com
License: MIT
Project-URL: Documentation, http://habanero.rtfd.org/
Project-URL: Source, https://github.com/sckott/habanero
Project-URL: Tracker, https://github.com/sckott/habanero/issues
Classifier: Development Status :: 5 - Production/Stable
Classifier: Intended Audience :: Science/Research
Classifier: Intended Audience :: Developers
Classifier: Topic :: Scientific/Engineering :: Bio-Informatics
Classifier: Natural Language :: English
Classifier: License :: OSI Approved :: MIT License
Classifier: Programming Language :: Python
Classifier: Programming Language :: Python :: 3
Classifier: Programming Language :: Python :: 3.6
Classifier: Programming Language :: Python :: 3.7
Classifier: Programming Language :: Python :: 3.8
Classifier: Programming Language :: Python :: 3.9
Classifier: Programming Language :: Python :: 3.10
Classifier: Programming Language :: Python :: 3.11
Classifier: Programming Language :: Python :: 3.12
Requires-Python: >=3.7
License-File: docs/LICENSE.rst
Requires-Dist: requests>=2.7.0
Requires-Dist: tqdm
Provides-Extra: test
Requires-Dist: pytest; extra == "test"
Provides-Extra: all
Requires-Dist: pytest; extra == "all"
Provides-Extra: bibtex
Requires-Dist: bibtexparser>=2.0.0; extra == "bibtex"
